odoo/addons/delivery_carrier_partner/README.rst
odoo/addons/delivery_carrier_partner/__init__.py
odoo/addons/delivery_carrier_partner/__manifest__.py
odoo/addons/delivery_carrier_partner/i18n/delivery_carrier_partner.pot
odoo/addons/delivery_carrier_partner/i18n/es.po
odoo/addons/delivery_carrier_partner/i18n/fr.po
odoo/addons/delivery_carrier_partner/i18n/it.po
odoo/addons/delivery_carrier_partner/models/__init__.py
odoo/addons/delivery_carrier_partner/models/delivery_carrier.py
odoo/addons/delivery_carrier_partner/readme/CONTRIBUTORS.md
odoo/addons/delivery_carrier_partner/readme/DESCRIPTION.md
odoo/addons/delivery_carrier_partner/static/description/icon.png
odoo/addons/delivery_carrier_partner/static/description/index.html
odoo/addons/delivery_carrier_partner/tests/__init__.py
odoo/addons/delivery_carrier_partner/tests/test_delivery_carrier_partner.py
odoo/addons/delivery_carrier_partner/views/delivery_carrier_views.xml
odoo_addon_delivery_carrier_partner-18.0.1.0.0.1.dist-info/METADATA
odoo_addon_delivery_carrier_partner-18.0.1.0.0.1.dist-info/WHEEL
odoo_addon_delivery_carrier_partner-18.0.1.0.0.1.dist-info/top_level.txt
odoo_addon_delivery_carrier_partner-18.0.1.0.0.1.dist-info/RECORD
